dirdb/__init__.py
dirdb/dirdb.py
dirdb-0.1.0.dist-info/LICENSE
dirdb-0.1.0.dist-info/METADATA
dirdb-0.1.0.dist-info/WHEEL
dirdb-0.1.0.dist-info/top_level.txt
dirdb-0.1.0.dist-info/RECORD
