Metadata-Version: 2.1
Name: dirdb
Version: 0.1.0
Summary: UNKNOWN
Home-page: https://gitlab.com/franksh/dirdb
Author: Frank S. Hestvik
Author-email: tristesse@gmail.com
License: MIT
Platform: UNKNOWN
Classifier: Programming Language :: Python :: 3
Classifier: License :: OSI Approved :: MIT License
Classifier: Operating System :: OS Independent
Requires-Python: >=3.6
Requires-Dist: filelock
